canonicalwebteam/__init__.py
canonicalwebteam/launchpad/__init__.py
canonicalwebteam/launchpad/models.py
tests/__init__.py
tests/test_launchpad.py
tests/fixtures/__init__.py
canonicalwebteam.launchpad-0.9.0.dist-info/LICENSE
canonicalwebteam.launchpad-0.9.0.dist-info/METADATA
canonicalwebteam.launchpad-0.9.0.dist-info/WHEEL
canonicalwebteam.launchpad-0.9.0.dist-info/top_level.txt
canonicalwebteam.launchpad-0.9.0.dist-info/RECORD
