Metadata-Version: 2.1
Name: canonicalwebteam.launchpad
Version: 0.9.0
Summary: Trigger builds of snaps and ubuntu imagesthrough the launchpad API.
Home-page: https://github.com/canonical-web-and-design/canonicalwebteam.launchpad
Author: Canonical webteam
Author-email: webteam@canonical.com
License-File: LICENSE
Requires-Dist: python-gnupg (>=0.4.6)
Requires-Dist: pytimeparse (==1.1.8)
Requires-Dist: humanize (==4.9.0)
